mqtts_lightning/__init__.py
mqtts_lightning/data/datamodule.py
mqtts_lightning/data/quantizer_datamodule.py
mqtts_lightning/model/LICENSE
mqtts_lightning/model/mqtts.py
mqtts_lightning/model/quantizer.py
mqtts_lightning/model/quantizer_lightning_module.py
mqtts_lightning/model/token_decoder_lightning_module.py
mqtts_lightning/model/modules/transducer.py
mqtts_lightning/model/modules/transformers.py
mqtts_lightning/model/modules/wildttstransformer.py
mqtts_lightning/preprocessor/preprocessor.py
mqtts_lightning/preprocessor/dataset/glob_wav_dataset.py
mqtts_lightning/preprocessor/dataset/jvs.py
mqtts_lightning/preprocessor/dataset/libritts.py
mqtts_lightning/preprocessor/dataset/parallel_audiobook_corpus.py
mqtts_lightning-0.1.1.dist-info/METADATA
mqtts_lightning-0.1.1.dist-info/WHEEL
mqtts_lightning-0.1.1.dist-info/RECORD
