Metadata-Version: 2.1
Name: mqtts-lightning
Version: 0.1.1
Summary: Add a short description here
Author-email: Wataru Nakata <wataru9871@gmail.com>
Requires-Python: >=3.8
Requires-Dist: hydra-core~=1.3.2
Requires-Dist: lightning~=2.0.3
Requires-Dist: matplotlib~=3.7.1
Requires-Dist: phonemizer~=3.2.1
Requires-Dist: pyopenjtalk[marine]~=0.3.0
Requires-Dist: soundfile~=0.12.1
Requires-Dist: torchaudio~=2.0.2
Requires-Dist: torch~=2.0.1
Requires-Dist: wandb~=0.15.4
Requires-Dist: webdataset~=0.2.48
